circuitydatabase/__init__.py
circuitydatabase/__main__.py
circuitydatabase/circuity.py
circuitydatabase/cli.py
circuitydatabase-18.dist-info/licenses/LICENSE
circuitydatabase-18.dist-info/METADATA
circuitydatabase-18.dist-info/WHEEL
circuitydatabase-18.dist-info/entry_points.txt
circuitydatabase-18.dist-info/top_level.txt
circuitydatabase-18.dist-info/RECORD
