Metadata-Version: 2.4
Name: circuitydatabase
Version: 18
License-Expression: MIT
Requires-Python: >=3
License-File: LICENSE
Requires-Dist: typer
Dynamic: license-file
